scio/__init__.py
scio/__init__.pyi
scio/eval/__init__.py
scio/eval/__init__.pyi
scio/eval/classification/__init__.py
scio/eval/classification/__init__.pyi
scio/eval/classification/benchmark.py
scio/eval/classification/discriminative_power.py
scio/eval/classification/roc.py
scio/py.typed
scio/recorder.py
scio/scores/__init__.py
scio/scores/__init__.pyi
scio/scores/base.py
scio/scores/classification/__init__.py
scio/scores/classification/__init__.pyi
scio/scores/classification/base.py
scio/scores/classification/baseline.py
scio/scores/classification/deepmahalanobis.py
scio/scores/classification/dknn.py
scio/scores/classification/energy.py
scio/scores/classification/featuresqueezing.py
scio/scores/classification/gradnorm.py
scio/scores/classification/gram.py
scio/scores/classification/isomax.py
scio/scores/classification/jointenergy.py
scio/scores/classification/jtla.py
scio/scores/classification/knn.py
scio/scores/classification/lid.py
scio/scores/classification/logit.py
scio/scores/classification/odds.py
scio/scores/classification/odin.py
scio/scores/classification/react.py
scio/scores/classification/relativemahalanobis.py
scio/scores/classification/softmax.py
scio/scores/classification/trust.py
scio/scores/utils/__init__.py
scio/scores/utils/__init__.pyi
scio/scores/utils/index.py
scio/scores/utils/index.pyi
scio/scores/utils/utils.py
scio/utils/__init__.py
scio/utils/__init__.pyi
scio/utils/enums.py
scio/utils/misc.py
scio_pypi-1.0.0.dist-info/WHEEL
scio_pypi-1.0.0.dist-info/METADATA
scio_pypi-1.0.0.dist-info/RECORD
