Metadata-Version: 2.3
Name: scio-pypi
Version: 1.0.0
Summary: Statistical Confidence from Internal Observations
Keywords: out-of-distribution detection,machine learning,statistics
Author: Élie Goudout
Author-email: Élie Goudout <elie.goudout@thalesgroup.com>
License: Copyright 2024–2025 THALES
Classifier: Development Status :: 4 - Beta
Classifier: Framework :: Pytest
Classifier: Intended Audience :: Developers
Classifier: Intended Audience :: Science/Research
Classifier: License :: OSI Approved :: MIT License
Classifier: Natural Language :: English
Classifier: Operating System :: OS Independent
Classifier: Programming Language :: Python :: 3
Classifier: Programming Language :: Python :: 3.12
Classifier: Programming Language :: Python :: 3.13
Classifier: Topic :: Scientific/Engineering :: Artificial Intelligence
Classifier: Topic :: Software Development :: Libraries
Classifier: Typing :: Typed
Requires-Dist: dill>=0.3.8
Requires-Dist: faiss-cpu>=1.12
Requires-Dist: lazy-loader>=0.4
Requires-Dist: matplotlib>=3.10
Requires-Dist: numpy>=2.2.2
Requires-Dist: pandas>=2.2.3
Requires-Dist: paramclasses>=0.4.0
Requires-Dist: rich>=13.9.4
Requires-Dist: scikit-learn>=1.6.1
Requires-Dist: scipy>=1.16
Requires-Dist: seaborn>=0.13.2
Requires-Dist: torch>=2.3
Requires-Dist: torchinfo>=1.8
Maintainer: Élie Goudout
Maintainer-email: Élie Goudout <elie.goudout@thalesgroup.com>
Requires-Python: >=3.12, <3.14
